qdyn/__init__.py
qdyn/analytical_pulse.py
qdyn/config.py
qdyn/io.py
qdyn/linalg.py
qdyn/memoize.py
qdyn/model.py
qdyn/prop_gate.py
qdyn/pulse.py
qdyn/shutil.py
qdyn/testing.py
qdyn/units.py
qdyn-25.3.1.dist-info/METADATA
qdyn-25.3.1.dist-info/WHEEL
qdyn-25.3.1.dist-info/top_level.txt
qdyn-25.3.1.dist-info/RECORD
