Metadata-Version: 2.4
Name: qdyn
Version: 25.3.1
Summary: Python package for interacting with the Fortran QDYN library and tools
Home-page: https://www.qdyn-library.net
Author: Michael Goerz
Author-email: mail@michaelgoerz.net
License: BSD license
Keywords: qdyn
Classifier: Development Status :: 4 - Beta
Classifier: Intended Audience :: Developers
Classifier: Intended Audience :: Education
Classifier: Intended Audience :: Science/Research
Classifier: License :: OSI Approved :: GNU General Public License v2 (GPLv2)
Classifier: Natural Language :: English
Classifier: Programming Language :: Python :: 3.7
Classifier: Programming Language :: Python :: 3.8
Classifier: Programming Language :: Python :: 3.9
Classifier: Natural Language :: English
Classifier: Topic :: Scientific/Engineering
Classifier: Topic :: Scientific/Engineering :: Physics
Requires-Python: >=3.7
Requires-Dist: numpy
Requires-Dist: matplotlib
Requires-Dist: scipy
Requires-Dist: sympy
Requires-Dist: click
Provides-Extra: dev
Requires-Dist: better-apidoc; extra == "dev"
Requires-Dist: coverage; extra == "dev"
Requires-Dist: coveralls; extra == "dev"
Requires-Dist: docs-versions-menu; extra == "dev"
Requires-Dist: flake8; extra == "dev"
Requires-Dist: gitpython; extra == "dev"
Requires-Dist: isort; extra == "dev"
Requires-Dist: ipython; extra == "dev"
Requires-Dist: pre-commit; extra == "dev"
Requires-Dist: pdbpp; extra == "dev"
Requires-Dist: pylint; extra == "dev"
Requires-Dist: pytest; extra == "dev"
Requires-Dist: pytest-cov; extra == "dev"
Requires-Dist: pytest-xdist; extra == "dev"
Requires-Dist: qutip; extra == "dev"
Requires-Dist: m2r; extra == "dev"
Requires-Dist: recommonmark; extra == "dev"
Requires-Dist: sphinx; extra == "dev"
Requires-Dist: sphinx-autobuild; extra == "dev"
Requires-Dist: sphinx-copybutton; extra == "dev"
Requires-Dist: sphinx-autodoc-typehints; extra == "dev"
Requires-Dist: sphinx_rtd_theme; extra == "dev"
Requires-Dist: twine; extra == "dev"
Requires-Dist: wheel; extra == "dev"
Requires-Dist: black; extra == "dev"
Dynamic: author
Dynamic: author-email
Dynamic: classifier
Dynamic: description
Dynamic: description-content-type
Dynamic: home-page
Dynamic: keywords
Dynamic: license
Dynamic: provides-extra
Dynamic: requires-dist
Dynamic: requires-python
Dynamic: summary
